CHO_ratio/__init__.py
CHO_ratio/main.py
CHO_ratio-1.0.0.dist-info/METADATA
CHO_ratio-1.0.0.dist-info/WHEEL
CHO_ratio-1.0.0.dist-info/top_level.txt
CHO_ratio-1.0.0.dist-info/RECORD
