Metadata-Version: 2.1
Name: CHO-ratio
Version: 1.0.0
Summary: UNKNOWN
Home-page: UNKNOWN
Author: atoy322
License: UNKNOWN
Platform: UNKNOWN
